{
    "Header_menu": {
        "Soccer": "Calcio",
        "Racing": "Da corsa",
        "Field Hockey": "Hockey su prato",
        "Basketball": "Pallacanestro",
        "Cricket": "Cricket",
        "Logout": "Disconnettersi",
        "Tennis sports": "Sport da tennis",
        "Badminton": "Badminton",
        "Kabaddi": "Kabaddi"
    },
    "Footer": {
        "About": "Di",
        "Contact": "Contatto",
        "Privacy_Policy": "politica sulla riservatezza",
        "Advertise_with_us": "Fate pubblicità con noi",
        "Blog": "blog",
        "Favourites": "Preferiti",
        "No_favourites": "Nessun preferito!",
        "Terms_and_Conditions": "Termini & Condizioni"
    },
    "Advertise_with_us": {
        "Advertise_with_us": "Fate pubblicità con noi",
        "Phone": "Telefono",
        "ready_to_text": "Pronto a raggiungere il nostro pubblico?",
        "advertise_submit_text": "La tua richiesta di annunci è stata inviata all'amministratore. ti contatterà presto.",
        "Company": "Azienda",
        "fill_form_text": "Compila questo modulo e il nostro staff ti contatterà presto.",
        "how_can_help": "Come possiamo aiutare ?"
    },
    "Contact_us": {
        "Submit": "Sottoscrivi",
        "Contact_Us": "Contattaci",
        "valid_email_msg": "Inserisci indirizzo email valido",
        "submit_another": "Invia un'altra risposta",
        "Subject": "Soggetto",
        "Full_Name": "Nome e cognome",
        "Message": "Messaggio",
        "Send_message": "Mandaci un messaggio",
        "required_field": "Questo campo è obbligatorio!",
        "Email": "E-mail",
        "response_submit_msg": "La tua risposta è stata inviata con successo."
    },
    "Blog_Module": {
        "Login": "Accesso",
        "Views": "Visualizzazioni",
        "Most_Read": "Più letti",
        "From_this_writer": "Da questo scrittore",
        "Delete": "Elimina",
        "Articles": "articoli",
        "browser_not_support_video_tag": "Il tuo browser non supporta il tag video.",
        "Posts": "Messaggi",
        "blogs": "Blog",
        "Comments": "Commenti",
        "Please_enter_your_comment": "Per favore inserisci il tuo commento",
        "Videos": "video",
        "Load_More": "Carica altro",
        "must_be_login_text": "Devi essere loggato per commentare.",
        "Delete_Comment": "Elimina commento",
        "Latest": "Più recente",
        "Readlist": "Readlist",
        "Search_results": "risultati di ricerca",
        "Post": "Inviare",
        "VIEW_MORE": "SCOPRI DI PIÙ",
        "want_to_delete": " Sei sicuro di voler eliminare questo commento ?",
        "Recent_Stories": "Storie recenti",
        "Keep": "conservare"
    },
    "Shared_module": {
        "Squad": "Squadra",
        "news": "notizia",
        "profile": "Profilo",
        "Recent_matches": "Partite recenti",
        "Manager": "Manager",
        "videos": "video",
        "Stadium": "stadio",
        "must_login_for_fav": "Devi essere loggato per aggiungere preferiti",
        "major_teams": "Principali squadre",
        "Founded": "Fondato",
        "quick_stats": "Statistiche rapide",
        "related_news": "Notizie correlate",
        "view_player": "Vedi giocatore",
        "latest": "Più recente",
        "no_live_commentry_available": "Ops! Nessun commento live disponibile al momento",
        "flash_score": "Punteggio Flash",
        "Abbreviation": "Abbreviazione"
    },
    "widgetModule": {
        "super": "Super",
        "starts": "inizia",
        "search_result": "risultati di ricerca",
        "comes_in_for": "entra per",
        "card": "carta",
        "terms": "condizioni",
        "Load_more": "Carica altro",
        "View_all": "Guarda tutto",
        "Match_updates": "Resta sintonizzato per gli aggiornamenti delle partite ...",
        "points": "Punti",
        "all_out": "Tutto fuori",
        "Raid_Points": "Punti Raid",
        "player_of_the_match": "Giocatore della partita",
        "venue": "Sede",
        "Results": "risultati",
        "continue_with_fb": "Continua con Facebook",
        "Table": "tavolo",
        "no_result_found": "Nessun risultato trovato!",
        "Capacity": "Capacità",
        "gets_a": "ottiene un",
        "wins_toss_select_choice": "vincere il sorteggio e selezionare la scelta di",
        "details": "Dettagli",
        "live": "Vivere",
        "time_out": "Tempo scaduto",
        "Series": "Serie",
        "Ends": "Ends",
        "Match_start": "La partita inizia tra ...",
        "sign_in": "Registrati",
        "result": "Risultato",
        "block_by_admin": "Questo ID e-mail \"ID e-mail\" è bloccato dall'amministratore. Si prega di contattare l'amministratore \"ID email dell'amministratore\"",
        "required_rate": "Tasso richiesto",
        "back": "Indietro",
        "Standings": "Classifiche",
        "Home": "Casa",
        "Stats": "Statistiche",
        "top_score": "Migliori marcatori",
        "Fixtures": "infissi",
        "match_is": "La partita è",
        "Privacy_policy": "Informativa sulla privacy",
        "agree_with_facebook": "Effettuando l'accesso con Google o Facebook, l'utente accetta SportsInfo",
        "opt_to": "optare per",
        "substitution": "Sostituzione",
        "do_or_die": "Fare o morire",
        "current_rate": "Tasso attuale",
        "Teams": "squadre",
        "Upcoming": "Prossime",
        "and": "e",
        "view_all": "Guarda tutto",
        "toss": "scossa",
        "sign_in_with_google": "Accedi con Google",
        "page_not_found": "Ops! Pagina non trovata."
    },
    "Cricket_Module": {
        "Fielding": "Fielding",
        "Series": "Serie",
        "News": "notizia",
        "Fall_of_Wickets": "Fall of Wickets",
        "Upcoming": "Prossime",
        "Total": "Totale",
        "no_venue_details_avail": "Nessun dato disponibile per questa partita!",
        "Extras": "extra",
        "Score": "Punto",
        "Info": "Informazioni",
        "Scorecard": "cartoncino segnapunti",
        "End_of_over": "Fine di oltre",
        "Recent_Fixtures": "Calendario recenti",
        "Teams": "squadre",
        "No_recent_results": "Nessun risultato recente",
        "Match": "Incontro",
        "Target": "Bersaglio",
        "Statistics": "statistica",
        "wickets": "wickets",
        "Match_is_cancelled": "La partita è stata annullata!",
        "Facts_and_Figures": "Fatti e cifre",
        "Results": "risultati",
        "No_recent_fixtures": "Nessun appuntamento recente",
        "1st_Inning": "1 ° Inning",
        "Batsman": "Battitore",
        "Wickets": "wickets",
        "Popular_Right_Now": "Popolare proprio ora",
        "2nd_Inning": "2 ° Inning",
        "Umpires": "arbitri",
        "Current_Series": "Serie attuali",
        "Recommended_Links": "Link consigliati",
        "no_probability_msg": "Nessun dato di probabilità disponibile per questa partita!",
        "Economy": "Economia",
        "Pitch_Condition": "Pitch Condition",
        "Top_Scorers": "Migliori marcatori",
        "Last_meetings": "Ultimi incontri",
        "Top": "Superiore",
        "This_over": "Questo finito",
        "Commentary": "Commento",
        "Weather_Condition": "Condizioni metereologiche",
        "Match_Refree": "Match Refree",
        "Fixtures": "infissi",
        "Standings": "Classifiche",
        "Win_Probability": "Vinci la probabilità",
        "Average": "Media",
        "Bowler": "bombetta",
        "Venue_Details": "Dettagli del luogo",
        "Summary": "Sommario",
        "Hawk_Eye": "Occhio di Falco",
        "Bowling": "Bowling",
        "Toss": "scossa",
        "Batting": "Batting",
        "Runs": "corre",
        "Top_Catches": "Le migliori catture",
        "No_Standings_available": "Nessuna classifica disponibile",
        "runs_per_over": "corre per oltre",
        "Outfield_Conditions": "Condizioni esterne"
    },
    "Kabaddi_Module": {
        "extra_points": "Punti extra",
        "venue_details": "Dettagli del luogo",
        "Info": "Informazioni",
        "Lineups": "Formazioni",
        "tackle_point": "Punti di contrasto",
        "match_stats": "Statistiche delle partite",
        "Tackle": "Affrontare",
        "raid": "incursione",
        "Cards": "Carte",
        "Statistics": "statistica",
        "commentary": "Commento",
        "all_out_point": "Tutti i punti"
    },
    "Home_Main_Page": {
        "View_All": " Guarda tutto",
        "Popular_Videos": "Video popolari",
        "Top_Highlights": "In evidenza"
    },
    "About_us": {
        "readers_text": "Cosa dicono i nostri lettori"
    },
    "Cricket_Module2": {
        "player": "giocatore",
        "International": "Internazionale",
        "Schedule": "Programma",
        "to": "a",
        "Yet": "Ancora",
        "High_Score": "Punteggio alto",
        "Domestic": "Domestico",
        "Did": "Did",
        "not": "non",
        "Catches": "Le catture",
        "bat": "un",
        "Economy_Rate": "Tasso di economia"
    },
    "Shared_Module2": {
        "Height": "Altezza",
        "Role": "Ruolo",
        "Born": "Nato",
        "Nationality": "Nazionalità",
        "Game_type": "Tipo di gioco",
        "Position": "Posizione",
        "Weight": "Peso",
        "TEAM": "SQUADRA",
        "Viewers": "Gli spettatori",
        "Batting_Stats": "Statistiche di battuta",
        "Batting_Style": "Stile di battuta",
        "Bowling_Stats": "Statistiche di bowling",
        "Bowling_Style": "Stile bowling",
        "Points_Table": "Tabella dei punti"
    },
    "Kabaddi_Module2": {
        "Zone": "Zona",
        "Green": "verde",
        "Yellow": "Giallo",
        "Tournament": "Torneo",
        "Red": "Rosso",
        "Successfull_tackles": "Affrontare con successo",
        "Super_Raids": "Super Raid",
        "Super_Tackles": "Super Tackles",
        "Tackle_Points": "Punti di contrasto",
        "Raids_Points": "Punti Raid",
        "Successfull_raids": "Incursioni riuscite"
    },
    "Blog_Module2": {
        "Search_results": "risultati di ricerca",
        "Edit": "modificare",
        "Recommended": "Consigliato",
        "Add_a_comment": "Aggiungi un commento",
        "Search_articles": "Cerca articoli"
    },
    "widget_Module2": {
        "Add_to_favourites": "Aggiungi ai preferiti",
        "No_data_available": "Nessun dato disponibile!",
        "No_team_fixtures": "Nessuna partita di squadra",
        "Recommended_Stories": "Storie consigliate",
        "No_team_results": "Nessun risultato di squadra",
        "Added_to_favourites": "Aggiunto ai preferiti",
        "No_Team_data_available": "Nessun dato disponibile sul team",
        "No_Team_squad": "Nessun dato disponibile per la squadra"
    },
    "Soccer_Module": {
        "Tournaments": "Tournaments",
        "Search_tournaments": "Search tournaments",
        "No_tournaments_data_available": "No tournaments data available!",
        "Clubs": "Clubs",
        "Goals": "Goals",
        "Assists": "Assists",
        "Cards": "Cards",
        "Own_Goals": "Own Goals",
        "Current_Tournaments": "Current Tournaments",
        "Shots": "Shots",
        "Shots_on_target": "Shots on target",
        "Shots_saved": "Shots saved",
        "Corners": "Corners",
        "Red_cards": "Red Cards",
        "Yellow_cards": "Yellow Cards",
        "Fouls": "Fouls",
        "Possession": "Possession",
        "half_time": "Half Time",
        "Country": "Country",
        "PLAYER": "PLAYER",
        "Minutes_Played": "Minutes Played",
        "Substituted_In": "Substituted In",
        "Substituted_Out": "Substituted Out",
        "Goals_Scored": "Goals Scored"
    },
    "Shared_Module3": {
        "Save": "Save",
        "Search_favourites": "Search favourites",
        "new_version_available": "New version of SportsInfo is available.",
        "Take_me_there": "Take me there",
        "cookie_text": "Hi! We use cookies on this website to help operate our site and for analytics purposes. For more on how we use cookies",
        "go": "go",
        "here": "here",
        "cookie_continue_use_text": "By continuing to use our services, you are giving us your consent to use cookies.",
        "Coming_Soon": "Coming Soon"
    },
    "widget_Module3": {
        "Cancel": "Cancel"
    }
}